Bohdan_drivers_report/__init__.py
Bohdan_drivers_report/main.py
bohdan_drivers_report-0.0.2.dist-info/METADATA
bohdan_drivers_report-0.0.2.dist-info/WHEEL
bohdan_drivers_report-0.0.2.dist-info/RECORD
