Metadata-Version: 2.4
Name: Bohdan_drivers_report
Version: 0.0.1
Summary: A small example package
Home-page: https://github.com/yourusername/mypackage
Author: Your Name
Author-email: BOhdan <boda57622@gmail.com>
License-Expression: MIT
Project-URL: Homepage, https://github.com/pypa/sampleproject
Project-URL: Issues, https://github.com/pypa/sampleproject/issues
Classifier: Programming Language :: Python :: 3
Classifier: Operating System :: OS Independent
Requires-Python: >=3.7
Dynamic: author
Dynamic: home-page
Dynamic: requires-python
